wield/bunch/__init__.py
wield/bunch/_version.py
wield/bunch/bunch.py
wield/bunch/deep_bunch.py
wield/bunch/depbunch.py
wield/bunch/hdf_deep_bunch.py
wield/bunch/interrupt_delay.py
wield/bunch/quickbunch.py
wield/bunch/shadow_bunch.py
wield/bunch/tag_bunch.py
wield.bunch-0.9.9.dist-info/Apache-2.0.txt
wield.bunch-0.9.9.dist-info/CC0-1.0.txt
wield.bunch-0.9.9.dist-info/METADATA
wield.bunch-0.9.9.dist-info/NOTICE
wield.bunch-0.9.9.dist-info/WHEEL
wield.bunch-0.9.9.dist-info/top_level.txt
wield.bunch-0.9.9.dist-info/RECORD
