Metadata-Version: 2.1
Name: wield.bunch
Version: 0.9.9
Summary: bunch container objects like Matlab structs
Home-page: https://github.com/wieldphysics/wield-bunch
Author: Lee McCuller
Author-email: mcculler@caltech.edu
License: Apache-2.0
Project-URL: Bug Tracker, https://github.com/wieldphysics/wield-bunch/issues
Project-URL: Source Code, https://github.com/wieldphysics/wield-bunch
Classifier: Intended Audience :: Science/Research
Classifier: License :: OSI Approved :: Apache Software License
Classifier: Operating System :: OS Independent
Classifier: Programming Language :: Python
Classifier: Programming Language :: Python :: 3
Classifier: Topic :: Scientific/Engineering :: Physics
License-File: LICENSES/Apache-2.0.txt
License-File: LICENSES/CC0-1.0.txt
License-File: NOTICE
